kanban/__init__.py
kanban/board.py
kanban/category_colors.py
kanban/main.py
kanban/storage.py
kanban/task.py
kanban/task_operations.py
kanban_cli-0.1.6.dist-info/licenses/LICENSE
scripts/check_rich.py
kanban_cli-0.1.6.dist-info/METADATA
kanban_cli-0.1.6.dist-info/WHEEL
kanban_cli-0.1.6.dist-info/entry_points.txt
kanban_cli-0.1.6.dist-info/top_level.txt
kanban_cli-0.1.6.dist-info/RECORD
