Metadata-Version: 2.4
Name: kanban-cli
Version: 0.1.6
Summary: A terminal-based Kanban board using Rich.
Author-email: Sergey Samoylov <linews@yandex.ru>
License: GPL-3.0-or-later
Requires-Python: >=3.9
License-File: LICENSE
Requires-Dist: rich>=13.0.0
Requires-Dist: platformdirs
Dynamic: license-file
